ratings/__init__.py
ratings/hereiam.py
ratings/inclusion.py
ratings/classification/__init__.py
ratings/inference/__init__.py
ratings/inference/inference.py
ratings/inference/utils.py
ratings/lattice/__init__.py
ratings/lattice/lattice_bayes.py
ratings/simulation/__init__.py
ratings/simulation/generation.py
ratings-0.3.6.dist-info/LICENSE
ratings-0.3.6.dist-info/METADATA
ratings-0.3.6.dist-info/WHEEL
ratings-0.3.6.dist-info/entry_points.txt
ratings-0.3.6.dist-info/top_level.txt
ratings-0.3.6.dist-info/RECORD
